waffle_cli/__init__.py
waffle_cli/application_logic/entities/cfn_stack_state.py
waffle_cli/application_logic/entities/deployment_setting.py
waffle_cli/application_logic/entities/deployment_state.py
waffle_cli/application_logic/entities/github_secret.py
waffle_cli/application_logic/entities/stack_type.py
waffle_cli/application_logic/gateway_interfaces/__init__.py
waffle_cli/application_logic/gateway_interfaces/certs.py
waffle_cli/application_logic/gateway_interfaces/deployment_settings.py
waffle_cli/application_logic/gateway_interfaces/deployment_states.py
waffle_cli/application_logic/gateway_interfaces/deployment_template_bucket.py
waffle_cli/application_logic/gateway_interfaces/github_secrets.py
waffle_cli/application_logic/gateway_interfaces/hosted_zones.py
waffle_cli/application_logic/gateway_interfaces/local_files.py
waffle_cli/application_logic/gateway_interfaces/stacks.py
waffle_cli/cli.py
waffle_cli/commands/__init__.py
waffle_cli/commands/command_type.py
waffle_cli/commands/configure_aws_profile.py
waffle_cli/commands/configure_deployment_domain.py
waffle_cli/commands/create_backend_service_wizard.py
waffle_cli/commands/create_cloudformation_wizard.py
waffle_cli/commands/create_database_wizard.py
waffle_cli/commands/create_deployment_certificate.py
waffle_cli/commands/create_deployment_settings.py
waffle_cli/commands/create_deployment_wizard.py
waffle_cli/commands/create_frontend_wizard.py
waffle_cli/commands/deploy_alerts.py
waffle_cli/commands/deploy_api.py
waffle_cli/commands/deploy_auth_userpool.py
waffle_cli/commands/deploy_cdn.py
waffle_cli/commands/deploy_cfn.py
waffle_cli/commands/deploy_db.py
waffle_cli/commands/deploy_deployment.py
waffle_cli/commands/deploy_ecs.py
waffle_cli/commands/deploy_github.py
waffle_cli/commands/deploy_vpc.py
waffle_cli/commands/generate_templates.py
waffle_cli/commands/list_deployments.py
waffle_cli/commands/set_deployment_defaults.py
waffle_cli/commands/utils/deploy_new_stack.py
waffle_cli/gateways/__init__.py
waffle_cli-0.0.6.dist-info/LICENSE
waffle_cli-0.0.6.dist-info/METADATA
waffle_cli-0.0.6.dist-info/WHEEL
waffle_cli-0.0.6.dist-info/entry_points.txt
waffle_cli-0.0.6.dist-info/RECORD
