Metadata-Version: 2.1
Name: waffle-cli
Version: 0.0.6
Summary: Waffle CLI
Home-page: https://github.com/WaffleCodeApp/waffle-cli
License: MIT
Author: Gergely Borgulya
Author-email: greg@wafflecode.com
Requires-Python: >=3.12,<3.13
Classifier: License :: OSI Approved :: MIT License
Classifier: Operating System :: OS Independent
Classifier: Programming Language :: Python :: 3
Classifier: Programming Language :: Python :: 3.12
Requires-Dist: awscli (>=1.32.44,<2.0.0)
Requires-Dist: boto3 (>=1.34.45,<2.0.0)
Requires-Dist: pydantic (>=2.6.1,<3.0.0)
Requires-Dist: troposphere[policy] (>=4.6.0,<5.0.0)
Project-URL: Repository, https://github.com/WaffleCodeApp/waffle-cli
